MANIFEST.in
README.md
setup.py
django_oak.egg-info/PKG-INFO
django_oak.egg-info/SOURCES.txt
django_oak.egg-info/dependency_links.txt
django_oak.egg-info/top_level.txt
oak/__init__.py
oak/decorators.py
oak/models.py
oak/tests.py
oak/urls.py
oak/views.py
oak/templates/base.html
oak/templates/oak/create.html
oak/templates/oak/delete.html
oak/templates/oak/detail.html
oak/templates/oak/list.html
oak/templates/oak/update.html