Metadata-Version: 1.1
Name: django-oak
Version: 0.1.2
Summary: Rapid prototyping for views and models in django.
Home-page: https://github.com/weholt/django-oak
Author: Thomas A. Weholt
Author-email: thomas@weholt.org
License: BSD License
Platform: UNKNOWN
Classifier: Development Status :: 3 - Alpha
Classifier: Environment :: Web Environment
Classifier: Framework :: Django
Classifier: Intended Audience :: Developers
Classifier: License :: OSI Approved :: BSD License
Classifier: Operating System :: OS Independent
Classifier: Programming Language :: Python
Classifier: Programming Language :: Python :: 2.7
Classifier: Topic :: Internet :: WWW/HTTP
Classifier: Topic :: Internet :: WWW/HTTP :: Dynamic Content
Requires: django
